setup.py
hv/__init__.py
hv/datastore.py
hv/entity.py
hv/util.py
hv.egg-info/PKG-INFO
hv.egg-info/SOURCES.txt
hv.egg-info/dependency_links.txt
hv.egg-info/requires.txt
hv.egg-info/top_level.txt
test/test_connection.py
test/test_operation.py