Metadata-Version: 1.0
Name: hv
Version: 0.1.1
Summary: postgresql connection manager for scalability freaks
Home-page: http://github.com/tetsuo/hypervault
Author: Onur Gunduz
Author-email: ogunduz@gmail.com
License: mit
Platform: UNKNOWN
